example/basic.py
limitys/__init__.py
limitys/__main__.py
limitys/cli.py
limitys/limitys.py
limitys/stop.py
limitys-2022.9.25.dist-info/LICENSE
limitys-2022.9.25.dist-info/METADATA
limitys-2022.9.25.dist-info/WHEEL
limitys-2022.9.25.dist-info/entry_points.txt
limitys-2022.9.25.dist-info/top_level.txt
limitys-2022.9.25.dist-info/RECORD
