Metadata-Version: 2.1
Name: limitys
Version: 2022.9.25
Summary: Overlap (Finnish: limitys) assesses sentences from constrained and overlapping vocabularies.
Author-email: Stefan Hagen <stefan@hagen.link>
Maintainer-email: Stefan Hagen <stefan@hagen.link>
Project-URL: Homepage, https://git.sr.ht/~sthagen/limitys
Project-URL: Bug-Tracker, https://todo.sr.ht/~sthagen/limitys
Project-URL: Documentation, https://codes.dilettant.life/docs/limitys
Project-URL: Source-Code, https://git.sr.ht/~sthagen/limitys
Project-URL: Test-Coverage, https://codes.dilettant.life/coverage/limitys
Keywords: developer-tools,surviving-process-bloat,requirements-engineering,validation,verification
Classifier: Development Status :: 3 - Alpha
Classifier: Intended Audience :: Developers
Classifier: License :: OSI Approved :: MIT License
Classifier: Programming Language :: Python :: 3.8
Classifier: Programming Language :: Python :: 3.9
Classifier: Programming Language :: Python :: 3.10
Requires-Python: >=3.8
License-File: LICENSE
Requires-Dist: PyYAML (>=6.0)
Requires-Dist: gensim (==4.2.0)
Requires-Dist: nltk (>=3.7)
Requires-Dist: numpy (>=1.23.3)
Requires-Dist: pandas (>=1.5.0)
Requires-Dist: scikit-learn (>=1.1.2)
Requires-Dist: typer (>=0.6.1)
Provides-Extra: dev
Requires-Dist: black ; extra == 'dev'
Requires-Dist: coverage ; extra == 'dev'
Requires-Dist: flake8 ; extra == 'dev'
Requires-Dist: hypothesis ; extra == 'dev'
Requires-Dist: mypy ; extra == 'dev'
Requires-Dist: pytest ; extra == 'dev'
Requires-Dist: pytest-cov ; extra == 'dev'
Requires-Dist: pytest-flake8 ; extra == 'dev'
